<?xml version="1.0" encoding="utf-8" ?>
<Namespace>
  <Pokemon>
    <id>Bulbasaur</id>
    <type>Grass</type>
    <hp>0</hp>
    <atk>0</atk>
    <def>0</def>
    <spd>0</spd>
    <spatk>0</spatk>
    <spdef>0</spdef>
    <Capabilites>
      <cap>Underdog</cap>
    </Capabilites>
    <TMHM>
      <tm></tm>
      <hm></hm>
    </TMHM>
    <Egg>
      <eg></eg>
    </Egg>
    <Tutor>
      <tut></tut>
    </Tutor>
    <size></size>
  </Pokemon>
  <Pokemon>
    <id>Charmander</id>
  </Pokemon>
    <id>Squirtle</id>
  <Pokemon>
    <id>Pikachu</id>
  </Pokemon>
    <id>Geodude</id>
  <Pokemon>
    <id>Oddish</id>
  </Pokemon>
  <Pokemon>
    <id>Growlithe</id>
  </Pokemon>
  <Pokemon>
    <id>Diglett</id>
  </Pokemon>
  <Pokemon>
    <id>Ponyta</id>
  </Pokemon>
  <Pokemon>
    <id>Magikarp</id>
  </Pokemon>
  <Pokemon>
    <id>Pidgey</id>
  </Pokemon>
  <Pokemon>
    <id>Weedle</id>
  </Pokemon>
  <Pokemon>
    <id>Caterpie</id>
  </Pokemon>
</Namespace>